smartsolve/__init__.py
smartsolve/evaluation.py
smartsolve/models.py
smartsolve/preprocessing.py
smartsolve-0.0.5.dist-info/METADATA
smartsolve-0.0.5.dist-info/WHEEL
smartsolve-0.0.5.dist-info/top_level.txt
smartsolve-0.0.5.dist-info/RECORD
